{
  "actions": [
    {
      "type": "deleteTable",
      "deleteTable": "category"
    },
    {
      "type": "createTable",
      "createTable": {
        "name": "category",
        "dartName": "Category",
        "module": "sync1",
        "schema": "public",
        "columns": [
          {
            "name": "id",
            "columnType": 7,
            "isNullable": false,
            "columnDefault": "gen_random_uuid_v7()",
            "dartType": "UuidValue?"
          },
          {
            "name": "title",
            "columnType": 0,
            "isNullable": false,
            "dartType": "String"
          },
          {
            "name": "lastModified",
            "columnType": 4,
            "isNullable": true,
            "dartType": "DateTime?"
          },
          {
            "name": "userId",
            "columnType": 6,
            "isNullable": false,
            "dartType": "int"
          }
        ],
        "foreignKeys": [],
        "indexes": [
          {
            "indexName": "category_pkey",
            "elements": [
              {
                "type": 0,
                "definition": "id"
              }
            ],
            "type": "btree",
            "isUnique": true,
            "isPrimary": true
          }
        ],
        "managed": true
      }
    }
  ],
  "warnings": [
    {
      "type": "tableDropped",
      "message": "One or more columns are added to table \"category\" which cannot be added in a table migration. The complete table will be deleted and recreated.",
      "table": "category",
      "columns": [
        "userId"
      ],
      "destrucive": true
    }
  ],
  "migrationApiVersion": 1
}